jdeppy/Bunsetsu.py
jdeppy/JDepP.py
jdeppy/Morph.py
jdeppy/Sentence.py
jdeppy/__init__.py
jdeppy-1.3.dist-info/LICENSE.txt
jdeppy-1.3.dist-info/METADATA
jdeppy-1.3.dist-info/WHEEL
jdeppy-1.3.dist-info/top_level.txt
jdeppy-1.3.dist-info/RECORD
